tidal_prediction/__init__.py
tidal_prediction/convert/__init__.py
tidal_prediction/convert/io_nc.py
tidal_prediction/tide/__init__.py
tidal_prediction/tide/nc.py
tidal_prediction/tide/tideconstit.py
tidal_prediction/tide/tidemodel.py
tidal_prediction/tide/tideutils.py
tidal_prediction-0.1.4.data/scripts/extract_local_model.py
tidal_prediction-0.1.4.data/scripts/predict_tide.py
tidal_prediction-0.1.4.dist-info/DESCRIPTION.rst
tidal_prediction-0.1.4.dist-info/METADATA
tidal_prediction-0.1.4.dist-info/RECORD
tidal_prediction-0.1.4.dist-info/WHEEL
tidal_prediction-0.1.4.dist-info/metadata.json
tidal_prediction-0.1.4.dist-info/top_level.txt
