Metadata-Version: 2.0
Name: tidal-prediction
Version: 0.1.4
Summary: UNKNOWN
Home-page: https://gitlab.com/jblarsen/tidal-prediction-python
Author: Jesper Baasch-Larsen
Author-email: jesper@baasch-larsen.dk
License: MIT License
Platform: UNKNOWN
Requires-Dist: astropy
Requires-Dist: configobj
Requires-Dist: netCDF4
Requires-Dist: numpy
Requires-Dist: scipy
